wlater_mcp/__init__.py
wlater_mcp/credentials.py
wlater_mcp/keep_client.py
wlater_mcp/selenium_auth.py
wlater_mcp/server.py
wlater_mcp/setup.py
wlater_mcp-0.2.0.dist-info/licenses/LICENSE
wlater_mcp-0.2.0.dist-info/METADATA
wlater_mcp-0.2.0.dist-info/WHEEL
wlater_mcp-0.2.0.dist-info/entry_points.txt
wlater_mcp-0.2.0.dist-info/top_level.txt
wlater_mcp-0.2.0.dist-info/RECORD
