Metadata-Version: 2.4
Name: wlater-mcp
Version: 0.2.0
Summary: Connect your AI assistant to Google Keep. Search, read, and manage your notes and lists through natural conversation.
Author: briansbrian
License-Expression: MIT
Project-URL: Homepage, https://github.com/briansbrian/wlater-McpServer
Project-URL: Repository, https://github.com/briansbrian/wlater-McpServer
Project-URL: Issues, https://github.com/briansbrian/wlater-McpServer/issues
Keywords: mcp,google-keep,ai-assistant,model-context-protocol
Classifier: Development Status :: 3 - Alpha
Classifier: Intended Audience :: Developers
Classifier: Programming Language :: Python :: 3
Classifier: Programming Language :: Python :: 3.8
Classifier: Programming Language :: Python :: 3.9
Classifier: Programming Language :: Python :: 3.10
Classifier: Programming Language :: Python :: 3.11
Classifier: Programming Language :: Python :: 3.12
Requires-Python: >=3.8
License-File: LICENSE
Requires-Dist: fastmcp>=0.1.0
Requires-Dist: gkeepapi>=0.15.0
Requires-Dist: keyring>=24.0.0
Requires-Dist: gpsoauth>=1.0.0
Provides-Extra: selenium
Requires-Dist: selenium>=4.0.0; extra == "selenium"
Provides-Extra: dev
Requires-Dist: pytest>=7.0.0; extra == "dev"
Requires-Dist: pytest-mock>=3.0.0; extra == "dev"
Requires-Dist: black>=23.0.0; extra == "dev"
Requires-Dist: mypy>=1.0.0; extra == "dev"
Dynamic: license-file
